setup.py
pysmarthome/__init__.py
pysmarthome/utils.py
pysmarthome.egg-info/PKG-INFO
pysmarthome.egg-info/SOURCES.txt
pysmarthome.egg-info/dependency_links.txt
pysmarthome.egg-info/not-zip-safe
pysmarthome.egg-info/requires.txt
pysmarthome.egg-info/top_level.txt
pysmarthome/controllers/__init__.py
pysmarthome/controllers/ac_controller.py
pysmarthome/controllers/device_controller.py
pysmarthome/controllers/multi_command_device_controller.py
pysmarthome/controllers/multi_command_rgb_lamp_controller.py
pysmarthome/controllers/pingable_device_controller.py
pysmarthome/controllers/plugin_controller.py
pysmarthome/controllers/rgb_lamp_controller.py
pysmarthome/controllers/tv_controller.py
pysmarthome/managers/__init__.py
pysmarthome/managers/manager.py
pysmarthome/managers/plugin_manager.py
pysmarthome/models/__init__.py
pysmarthome/models/acs_model.py
pysmarthome/models/colors_model.py
pysmarthome/models/device_model.py
pysmarthome/models/multi_command_devices_model.py
pysmarthome/models/multi_command_rgb_lamps_model.py
pysmarthome/models/plugins_model.py
pysmarthome/models/rgb_light_model.py
pysmarthome/models/scene_model.py
pysmarthome/models/tvs_model.py