Metadata-Version: 2.1
Name: pysmarthome
Version: 3.1.0
Summary: A python library that aims to provide utilities to implement smart home systems
Home-page: https://github.com/filipealvesdef/pysmarthome/
Author: Filipe Alves
Author-email: filipe.alvesdefernando@gmail.com
License: UNKNOWN
Platform: UNKNOWN
